functionalmf/__init__.py
functionalmf/elliptical_slice.py
functionalmf/factor.py
functionalmf/fast_mvn.py
functionalmf/gass.py
functionalmf/genlasso.py
functionalmf/pgds.py
functionalmf/utils.py
functionalmf-1.0.dist-info/LICENSE
functionalmf-1.0.dist-info/METADATA
functionalmf-1.0.dist-info/WHEEL
functionalmf-1.0.dist-info/top_level.txt
functionalmf-1.0.dist-info/RECORD
