Metadata-Version: 2.1
Name: functionalmf
Version: 1.0
Summary: Bayesian factorization of matrices where every entry is a curve or function rather than a scalar.
Home-page: http://www.github.com/tansey/functionalmf
Author: Wesley Tansey
Author-email: wes.tansey@gmail.com
License: GNU GPLv3
Keywords: monte-carlo,lasso,trend-filtering,smoothing,tensor-factorization,matrix-factorization
Platform: ALL
Classifier: Intended Audience :: Science/Research
Classifier: Programming Language :: Python
Requires-Dist: numpy
Requires-Dist: scipy
Requires-Dist: matplotlib
Requires-Dist: pypolyagamma
Requires-Dist: seaborn
Requires-Dist: scikit-sparse
